[
  { "q": "Professor: Joãozinho, diz-me uma palavra com muitas letras.", "a": "Correio!" },
  { "q": "Professor: Onde fica a Cordilheira dos Andes?", "a": "Aluno: Se o senhor não se lembra onde a deixou, eu é que não sei!" },
  { "q": "Professor: Conjuga o verbo andar.", "a": "Aluno: Eu ando, tu andas... — Mais depressa! — Eu corro, tu corres!" },
  { "q": "Professor: Se tens 5 maçãs e te tiro 3, com quantas ficas?", "a": "Furioso!" },
  { "q": "Professor: Por que chegaste atrasado?", "a": "Por causa de um sinal na estrada que dizia 'Escola — devagar'." },
  { "q": "Professor: Joãozinho, usa 'rendimento' numa frase.", "a": "Eu não estava a dormir, professor, estava a render-me ao sono." },
  { "q": "Professor: O que é a vírgula?", "a": "É uma pausa para respirar... como esta que vou fazer antes de dizer que não estudei." },
  { "q": "Aluno: Professor, eu posso ser castigado por algo que não fiz?", "a": "Claro que não. — Ainda bem, porque não fiz os trabalhos de casa." },
  { "q": "Professor: Diz-me três famílias de instrumentos musicais.", "a": "A família do tambor, a família da guitarra e a família do meu vizinho que toca às 3h." },
  { "q": "Professor: Quanto é metade de oito?", "a": "Em pé é zero, deitado é três!" },
  { "q": "Professor: Por que escreveste a redação tão curta?", "a": "Estava a poupar tinta para o ambiente." },
  { "q": "Professor: O que sabes sobre o Mar Morto?", "a": "Não sabia que estava doente!" },
  { "q": "Professor: Cita um líquido que não congele.", "a": "A água a ferver." },
  { "q": "Professor: Joãozinho, sabes o que é a hipotenusa?", "a": "É a tia do hipopótamo?" },
  { "q": "Professor: Como se chama quem continua a falar mesmo sem ninguém ouvir?", "a": "Professor!" },
  { "q": "Aluno: Professor, podia baixar a nota deste teste?", "a": "Mais? Já está em 4! — Não, baixá-la para eu não a ver." },
  { "q": "Professor: Quem assinou a Magna Carta?", "a": "Não fui eu, professor, juro!" },
  { "q": "Professor: O que é um sinónimo?", "a": "É a palavra que usamos quando não sabemos escrever a primeira." },
  { "q": "Professor: Joãozinho, diz uma frase com 'mas'.", "a": "Eu estudei... mas esqueci-me." },
  { "q": "Professor: Por que estás a olhar para o relógio?", "a": "Para não perder a aula... de vista." },
  { "q": "Professor: Resolve esta equação.", "a": "Aluno: Já resolvi — decidi que não vale a pena!" },
  { "q": "Professor: O que aprendeste hoje?", "a": "Aparentemente não o suficiente, porque me mandou voltar amanhã." },
  { "q": "Professor: Diz-me um animal invertebrado.", "a": "O aluno que dorme na última fila." },
  { "q": "Aluno: Professor, existe trabalho de casa de recreio?", "a": "Não. — Então faltei à única aula que valia a pena." },
  { "q": "Professor: O que é a fotossíntese?", "a": "É quando tiramos uma fotografia com síntese." },
  { "q": "Professor: Por que copiaste o teste do teu colega?", "a": "Não copiei! Só confirmei que tínhamos os mesmos erros." },
  { "q": "Professor: Qual é a capital de França?", "a": "F." },
  { "q": "Professor: Diz uma palavra que comece e acabe com a letra A.", "a": "Aula... que eu queria que acabasse!" },
  { "q": "Professor: O que é a gravidade?", "a": "É o que me puxa para a cama todas as manhãs." },
  { "q": "Aluno: Professor, porque é que me deu zero?", "a": "Porque não há nota mais baixa." },
  { "q": "Professor: Conta até dez.", "a": "1, 2, 3, 4, 5, 6, 7, 8, 9, 10... e o intervalo, quando é?" },
  { "q": "Professor: Por que trouxeste uma escada para a aula?", "a": "Porque hoje é aula de ensino superior." },
  { "q": "Professor: O que é o pretérito perfeito?", "a": "É o intervalo que já passou e era perfeito." },
  { "q": "Professor: Define 'paralelas'.", "a": "São as linhas que nunca se encontram... como eu e a boa nota." },
  { "q": "Professor: Por que tens o caderno em branco?", "a": "Para combinar com a minha mente nesta altura da manhã." },
  { "q": "Professor: Quem descobriu o Brasil?", "a": "Quem o tinha perdido!" },
  { "q": "Professor: Quanto é 2 + 2?", "a": "Depende. Estamos a comprar ou a vender?" }
]
