{"id":"aelassas__wexflow","name":"wexflow","owner":"aelassas","desc":"Workflow Automation Engine","lang":"C#","langColor":"#178600","stars":838,"forks":190,"issues":0,"d7":1,"boot":false,"vel":1,"score":7.018,"cats":["automation"],"lists":0,"hn":null,"license":"MIT","created":"2022-10-29","pushed":"2026-07-17","topics":["automation","cross-platform","csharp","dotnet","etl","scheduler"],"isNew":false,"descFull":"Workflow Automation Engine","homepage":"https://wexflow.github.io","avatar":"https://avatars.githubusercontent.com/u/1339626?v=4","ghUrl":"https://github.com/aelassas/wexflow","defaultBranch":"main","watchers":36,"langs":[{"name":"C#","color":"#178600","pct":81},{"name":"JavaScript","color":"#f1e05a","pct":14},{"name":"Inno Setup","color":"#264b99","pct":1},{"name":"HTML","color":"#e34c26","pct":1},{"name":"CSS","color":"#663399","pct":1},{"name":"Batchfile","color":"#C1F12E","pct":1}],"hnPosts":[],"awesomeIn":[],"starsSeries":[["2026-07-14",837],["2026-07-20",838]]}