{"id":"apache__superset","name":"superset","owner":"apache","desc":"Apache Superset is a Data Visualization and Data Exploration Platform","lang":"TypeScript","langColor":"#3178c6","stars":73680,"forks":17814,"issues":842,"d7":53,"boot":false,"vel":53,"score":14.267,"cats":["science"],"lists":0,"hn":null,"license":"Apache-2.0","created":"2015-07-21","pushed":"2026-07-06","topics":["analytics","apache","apache-superset","asf","bi","business-analytics"],"isNew":false,"descFull":"Apache Superset is a Data Visualization and Data Exploration Platform","homepage":"https://superset.apache.org/","avatar":"https://avatars.githubusercontent.com/u/47359?v=4","ghUrl":"https://github.com/apache/superset","defaultBranch":"master","langs":[{"name":"TypeScript","color":"#3178c6","pct":100}],"hnPosts":[],"awesomeIn":[],"starsSeries":[["2026-06-20",73485],["2026-06-26",73604],["2026-07-02",73680]]}