{"id":"apache__devlake","name":"devlake","owner":"apache","desc":"Apache DevLake is an open-source dev data platform to ingest, analyze, and visualize the fragmented data from DevOps tools, extracting insights for engineering…","lang":"Go","langColor":"#00ADD8","stars":3057,"forks":768,"issues":71,"d7":5,"boot":false,"vel":5,"score":9.417,"cats":["devops","science"],"lists":0,"hn":null,"license":"Apache-2.0","created":"2021-07-08","pushed":"2026-07-02","topics":["dashboard-friendly","data","data-analysis","data-engineering","data-integration","data-transfers"],"isNew":false,"descFull":"Apache DevLake is an open-source dev data platform to ingest, analyze, and visualize the fragmented data from DevOps tools, extracting insights for engineering excellence, developer experience, and community growth.","homepage":"https://devlake.apache.org/","avatar":"https://avatars.githubusercontent.com/u/47359?v=4","ghUrl":"https://github.com/apache/devlake","defaultBranch":"main","watchers":44,"langs":[{"name":"Go","color":"#00ADD8","pct":88},{"name":"TypeScript","color":"#3178c6","pct":9},{"name":"Python","color":"#3572A5","pct":2},{"name":"Shell","color":"#89e051","pct":0},{"name":"Go Template","color":"#00ADD8","pct":0},{"name":"Dockerfile","color":"#384d54","pct":0}],"hnPosts":[],"awesomeIn":[],"starsSeries":[["2026-06-21",3049],["2026-06-27",3057]]}