{"id":"ashtonjamesd__lavandula","name":"lavandula","owner":"ashtonjamesd","desc":"a lightweight web framework in c","lang":"C","langColor":"#555555","stars":986,"forks":48,"issues":5,"d7":26,"boot":true,"vel":26,"score":11.291,"cats":["web"],"lists":0,"hn":null,"license":"MIT","created":"2025-09-26","pushed":"2026-01-13","topics":["backend","c","framework","http","json","web"],"isNew":true,"descFull":"a lightweight web framework in c","homepage":"","avatar":"https://avatars.githubusercontent.com/u/121163457?v=4","ghUrl":"https://github.com/ashtonjamesd/lavandula","defaultBranch":"main","langs":[{"name":"C","color":"#555555","pct":100}],"hnPosts":[],"awesomeIn":[],"starsSeries":[["2026-06-21",986]]}