{"id":"astro-stack__django-orbit","name":"django-orbit","owner":"astro-stack","desc":"AI agent-native observability and debugging for Django.","lang":"Python","langColor":"#3572A5","stars":174,"forks":7,"issues":2,"d7":0,"boot":false,"vel":0,"score":5.141,"cats":["devops"],"lists":0,"hn":null,"license":"MIT","created":"2025-12-15","pushed":"2026-07-02","topics":["ai","ai-agents","debugging","debugging-tool","django","observability"],"isNew":true,"descFull":"AI agent-native observability and debugging for Django.","homepage":"https://labs.wearehik.com/django-orbit","avatar":"https://avatars.githubusercontent.com/u/154466907?v=4","ghUrl":"https://github.com/astro-stack/django-orbit","defaultBranch":"main","langs":[{"name":"Python","color":"#3572A5","pct":100}],"hnPosts":[],"awesomeIn":[],"starsSeries":[["2026-06-21",173],["2026-06-27",174],["2026-07-03",174]]}