{"id":"Automattic__harper","name":"harper","owner":"Automattic","desc":"Offline, privacy-first grammar checker. Fast, open-source, Rust-powered","lang":"Rust","langColor":"#dea584","stars":11134,"forks":400,"issues":686,"d7":17,"boot":false,"vel":17,"score":11.654,"cats":["tools"],"lists":0,"hn":null,"license":"Apache-2.0","created":"2023-10-22","pushed":"2026-07-20","topics":["chrome-extension","developer-tools","english-language","grammar-checker","nodejs","react"],"isNew":false,"descFull":"Offline, privacy-first grammar checker. Fast, open-source, Rust-powered","homepage":"https://writewithharper.com","avatar":"https://avatars.githubusercontent.com/u/887802?v=4","ghUrl":"https://github.com/Automattic/harper","defaultBranch":"master","watchers":26,"langs":[{"name":"Rust","color":"#dea584","pct":76},{"name":"TypeScript","color":"#3178c6","pct":11},{"name":"Svelte","color":"#ff3e00","pct":7},{"name":"HTML","color":"#e34c26","pct":3},{"name":"JavaScript","color":"#f1e05a","pct":1},{"name":"Just","color":"#384d54","pct":1}],"hnPosts":[],"awesomeIn":[],"starsSeries":[["2026-06-20",10898],["2026-06-26",10935],["2026-07-02",11002],["2026-07-08",11044],["2026-07-14",11117],["2026-07-20",11134]]}