{"id":"Azure__logicapps","name":"logicapps","owner":"Azure","desc":"Azure Logic Apps labs, samples, and tools","lang":"ABAP","langColor":"#8b949e","stars":423,"forks":319,"issues":63,"d7":0,"boot":false,"vel":0,"score":5.356,"cats":["cloud"],"lists":0,"hn":null,"license":"MIT","created":"2017-05-19","pushed":"2026-06-24","topics":["azure","logic-apps","serverless"],"isNew":false,"descFull":"Azure Logic Apps labs, samples, and tools","homepage":"","avatar":"https://avatars.githubusercontent.com/u/6844498?v=4","ghUrl":"https://github.com/Azure/logicapps","defaultBranch":"master","langs":[{"name":"ABAP","color":"#8b949e","pct":100}],"hnPosts":[],"awesomeIn":[],"starsSeries":[["2026-06-21",423],["2026-06-27",423],["2026-07-03",423]]}