{"id":"caojiaolong__spaces-index","name":"spaces-index","owner":"caojiaolong","desc":"🌟本项目自动抓取并索引科学空间的文章元数据，按研究主题进行规则分类，方便在 GitHub 上快速浏览并跳转到原文。","lang":"Python","langColor":"#3572A5","stars":282,"forks":10,"issues":0,"d7":1,"boot":false,"vel":1,"score":7.071,"cats":["ai"],"lists":0,"hn":null,"license":"MIT","created":"2026-04-30","pushed":"2026-07-23","topics":["artificial-intelligence","blogs","machine-learning","math","mathematics"],"isNew":true,"descFull":"🌟本项目自动抓取并索引科学空间的文章元数据，按研究主题进行规则分类，方便在 GitHub 上快速浏览并跳转到原文。","homepage":"https://caojiaolong.github.io/spaces-index/","avatar":"https://avatars.githubusercontent.com/u/18239971?v=4","ghUrl":"https://github.com/caojiaolong/spaces-index","defaultBranch":"main","watchers":0,"langs":[{"name":"Python","color":"#3572A5","pct":50},{"name":"JavaScript","color":"#f1e05a","pct":34},{"name":"CSS","color":"#663399","pct":15},{"name":"HTML","color":"#e34c26","pct":2}],"hnPosts":[],"awesomeIn":[],"starsSeries":[["2026-06-21",260],["2026-06-27",267],["2026-07-03",276],["2026-07-10",281],["2026-07-16",281],["2026-07-22",282]]}