{"id":"crate__crate","name":"crate","owner":"crate","desc":"CrateDB is a distributed and scalable SQL database for storing and analyzing massive amounts of data in near real-time, even with complex queries. It is Postgr…","lang":"Java","langColor":"#b07219","stars":4414,"forks":601,"issues":313,"d7":0,"boot":false,"vel":0,"score":7.084,"cats":["database"],"lists":0,"hn":null,"license":"Apache-2.0","created":"2013-04-10","pushed":"2026-06-27","topics":["analytics","big-data","cratedb","database","dbms","distributed"],"isNew":false,"descFull":"CrateDB is a distributed and scalable SQL database for storing and analyzing massive amounts of data in near real-time, even with complex queries. It is PostgreSQL-compatible, and based on Lucene.","homepage":"https://cratedb.com/database","avatar":"https://avatars.githubusercontent.com/u/4048232?v=4","ghUrl":"https://github.com/crate/crate","defaultBranch":"master","watchers":169,"langs":[{"name":"Java","color":"#b07219","pct":100},{"name":"Python","color":"#3572A5","pct":0},{"name":"ANTLR","color":"#9DC3FF","pct":0},{"name":"Shell","color":"#89e051","pct":0}],"hnPosts":[],"awesomeIn":[],"starsSeries":[["2026-06-21",4414],["2026-06-27",4414]]}