{"id":"davidroyer__vue2-editor","name":"vue2-editor","owner":"davidroyer","desc":"A text editor using Vue.js and Quill","lang":"JavaScript","langColor":"#f1e05a","stars":2518,"forks":356,"issues":4,"d7":5,"boot":true,"vel":5,"score":9.203,"cats":["tools"],"lists":0,"hn":null,"license":"MIT","created":"2016-11-29","pushed":"2026-06-24","topics":["editor","quill","quilljs","vue","vue2"],"isNew":false,"descFull":"A text editor using Vue.js and Quill","homepage":"","avatar":"https://avatars.githubusercontent.com/u/8834693?v=4","ghUrl":"https://github.com/davidroyer/vue2-editor","defaultBranch":"master","watchers":36,"langs":[{"name":"JavaScript","color":"#f1e05a","pct":59},{"name":"Vue","color":"#41b883","pct":32},{"name":"SCSS","color":"#c6538c","pct":8}],"hnPosts":[],"awesomeIn":[],"starsSeries":[["2026-06-21",2518]]}