{"id":"defold__defold","name":"defold","owner":"defold","desc":"Defold is a completely free to use game engine for development of desktop, mobile and web games.","lang":"C++","langColor":"#f34b7d","stars":6197,"forks":440,"issues":970,"d7":6,"boot":false,"vel":6,"score":10.033,"cats":["games"],"lists":0,"hn":null,"license":null,"created":"2012-05-13","pushed":"2026-07-24","topics":["c-plus-plus","clojure","defold","game-development","game-engine","gamedev"],"isNew":false,"descFull":"Defold is a completely free to use game engine for development of desktop, mobile and web games.","homepage":"https://www.defold.com","avatar":"https://avatars.githubusercontent.com/u/1090871?v=4","ghUrl":"https://github.com/defold/defold","defaultBranch":"dev","watchers":64,"langs":[{"name":"C++","color":"#f34b7d","pct":36},{"name":"C","color":"#555555","pct":25},{"name":"Clojure","color":"#db5855","pct":18},{"name":"Java","color":"#b07219","pct":7},{"name":"Python","color":"#3572A5","pct":3},{"name":"Lua","color":"#000080","pct":3}],"hnPosts":[],"awesomeIn":[],"starsSeries":[["2026-06-20",6135],["2026-06-26",6149],["2026-07-02",6162],["2026-07-08",6175],["2026-07-14",6188],["2026-07-20",6197]]}