{"id":"evilsocket__opensnitch","name":"opensnitch","owner":"evilsocket","desc":"OpenSnitch is a GNU/Linux interactive application firewall inspired by Little Snitch.","lang":"Python","langColor":"#3572A5","stars":13831,"forks":647,"issues":177,"d7":11,"boot":false,"vel":11,"score":11.329,"cats":["security"],"lists":1,"hn":null,"license":"GPL-3.0","created":"2017-04-16","pushed":"2026-06-21","topics":["application-firewall","data-breach","firewall","linux","networking","security"],"isNew":false,"descFull":"OpenSnitch is a GNU/Linux interactive application firewall inspired by Little Snitch.","homepage":"","avatar":"https://avatars.githubusercontent.com/u/86922?v=4","ghUrl":"https://github.com/evilsocket/opensnitch","defaultBranch":"master","watchers":209,"langs":[{"name":"Python","color":"#3572A5","pct":58},{"name":"Go","color":"#00ADD8","pct":31},{"name":"C","color":"#555555","pct":10},{"name":"Shell","color":"#89e051","pct":1},{"name":"Makefile","color":"#427819","pct":0},{"name":"QMake","color":null,"pct":0}],"hnPosts":[],"awesomeIn":[{"list":"security","label":"Awesome Security","emoji":"🛡️","heading":"Monitoring / Logging","category":"security"}],"starsSeries":[["2026-06-20",13820],["2026-06-26",13831]]}