{"id":"future-architect__vuls","name":"vuls","owner":"future-architect","desc":"Agent-less vulnerability scanner for Linux, FreeBSD, Container, WordPress, Programming language libraries, Network devices","lang":"Go","langColor":"#00ADD8","stars":12201,"forks":1236,"issues":87,"d7":3,"boot":false,"vel":3,"score":9.632,"cats":["security"],"lists":0,"hn":null,"license":"GPL-3.0","created":"2016-03-27","pushed":"2026-07-01","topics":["administrator","cybersecurity","freebsd","go","golang","linux"],"isNew":false,"descFull":"Agent-less vulnerability scanner for Linux, FreeBSD, Container, WordPress, Programming language libraries, Network devices","homepage":"https://vuls.io/","avatar":"https://avatars.githubusercontent.com/u/14890632?v=4","ghUrl":"https://github.com/future-architect/vuls","defaultBranch":"master","watchers":324,"langs":[{"name":"Go","color":"#00ADD8","pct":100},{"name":"Makefile","color":"#427819","pct":0},{"name":"Dockerfile","color":"#384d54","pct":0}],"hnPosts":[],"awesomeIn":[],"starsSeries":[["2026-06-20",12197],["2026-06-26",12201]]}