{"id":"golf-mcp__golf","name":"golf","owner":"golf-mcp","desc":"Production-Ready MCP Server Framework • Build, deploy & scale secure AI agent infrastructure • Includes Auth, Observability, Debugger, Telemetry & Runtime • Ru…","lang":"Python","langColor":"#3572A5","stars":834,"forks":69,"issues":0,"d7":0,"boot":false,"vel":0,"score":4.244,"cats":["devops"],"lists":0,"hn":null,"license":"Apache-2.0","created":"2025-02-24","pushed":"2026-05-08","topics":["agent-runtime","ai","ai-agent","ai-agent-tools","ai-agents","ai-platform"],"isNew":false,"descFull":"Production-Ready MCP Server Framework • Build, deploy & scale secure AI agent infrastructure • Includes Auth, Observability, Debugger, Telemetry & Runtime • Run real-world MCPs powering AI Agents ","homepage":"https://golf.dev/","avatar":"https://avatars.githubusercontent.com/u/199558826?v=4","ghUrl":"https://github.com/golf-mcp/golf","defaultBranch":"main","watchers":6,"langs":[{"name":"Python","color":"#3572A5","pct":100}],"hnPosts":[],"awesomeIn":[],"starsSeries":[["2026-06-21",834],["2026-06-27",834],["2026-07-03",834],["2026-07-10",833],["2026-07-16",834],["2026-07-22",834]]}