{"id":"googleapis__google-api-php-client","name":"google-api-php-client","owner":"googleapis","desc":"A PHP client library for accessing Google APIs","lang":"PHP","langColor":"#4F5D95","stars":9799,"forks":3545,"issues":15,"d7":1,"boot":false,"vel":1,"score":7.692,"cats":[],"lists":0,"hn":null,"license":"Apache-2.0","created":"2013-08-16","pushed":"2026-06-29","topics":[],"isNew":false,"descFull":"A PHP client library for accessing Google APIs","homepage":"http://googleapis.github.io/google-api-php-client/","avatar":"https://avatars.githubusercontent.com/u/16785467?v=4","ghUrl":"https://github.com/googleapis/google-api-php-client","defaultBranch":"main","langs":[{"name":"PHP","color":"#4F5D95","pct":100}],"hnPosts":[],"awesomeIn":[],"starsSeries":[["2026-06-21",9794],["2026-06-27",9794],["2026-07-03",9798],["2026-07-10",9798],["2026-07-16",9799]]}