{"id":"HandBrake__HandBrake","name":"HandBrake","owner":"HandBrake","desc":"HandBrake's development repository","lang":"C","langColor":"#555555","stars":23673,"forks":1650,"issues":285,"d7":29,"boot":false,"vel":29,"score":12.61,"cats":[],"lists":0,"hn":null,"license":null,"created":"2015-08-22","pushed":"2026-06-30","topics":["gplv2","multi-platform","video-transcoding"],"isNew":false,"descFull":"HandBrake's development repository ","homepage":"https://handbrake.fr","avatar":"https://avatars.githubusercontent.com/u/627269?v=4","ghUrl":"https://github.com/HandBrake/HandBrake","defaultBranch":"master","langs":[{"name":"C","color":"#555555","pct":100}],"hnPosts":[],"awesomeIn":[],"starsSeries":[["2026-06-20",23565],["2026-06-26",23640],["2026-07-02",23673]]}