{"id":"HaxeFlixel__flixel","name":"flixel","owner":"HaxeFlixel","desc":"Free, cross-platform 2D game engine powered by Haxe and OpenFL","lang":"Haxe","langColor":"#8b949e","stars":2192,"forks":506,"issues":299,"d7":3,"boot":true,"vel":3,"score":8.588,"cats":["games"],"lists":0,"hn":null,"license":"MIT","created":"2011-07-25","pushed":"2026-06-18","topics":["2d-game-engine","cross-platform","flixel","game-engine","haxe","haxeflixel"],"isNew":false,"descFull":"Free, cross-platform 2D game engine powered by Haxe and OpenFL","homepage":"https://haxeflixel.com/","avatar":"https://avatars.githubusercontent.com/u/4309553?v=4","ghUrl":"https://github.com/HaxeFlixel/flixel","defaultBranch":"dev","watchers":null,"langs":[{"name":"Haxe","color":"#8b949e","pct":100}],"hnPosts":[],"awesomeIn":[],"starsSeries":[["2026-06-20",2192]]}