{"id":"JanDeDobbeleer__oh-my-posh","name":"oh-my-posh","owner":"JanDeDobbeleer","desc":"The most customisable and low-latency cross platform/shell prompt renderer","lang":"Go","langColor":"#00ADD8","stars":22934,"forks":2750,"issues":33,"d7":6,"boot":false,"vel":6,"score":10.666,"cats":[],"lists":0,"hn":null,"license":"MIT","created":"2019-03-13","pushed":"2026-06-26","topics":["bash","cmd","fish","fish-shell","git","golang"],"isNew":false,"descFull":"The most customisable and low-latency cross platform/shell prompt renderer","homepage":"https://ohmyposh.dev","avatar":"https://avatars.githubusercontent.com/u/2492783?v=4","ghUrl":"https://github.com/JanDeDobbeleer/oh-my-posh","defaultBranch":"main","langs":[{"name":"Go","color":"#00ADD8","pct":100}],"hnPosts":[],"awesomeIn":[],"starsSeries":[["2026-06-21",22928],["2026-06-27",22934]]}