{"id":"jbwinters__jacquard-lang","name":"jacquard-lang","owner":"jbwinters","desc":"Jacquard is a small programming language designed for a regime in which most code is written by machine-learning models and reviewed by people.","lang":"OCaml","langColor":"#8b949e","stars":93,"forks":2,"issues":4,"d7":0,"boot":false,"vel":0,"score":8.69,"cats":[],"lists":0,"hn":{"points":102,"comments":58},"license":"Apache-2.0","created":"2026-07-06","pushed":"2026-07-20","topics":["algebraic-effects","capability-security","content-addressing","language-design","ocaml","probabilistic-programming"],"isNew":true,"descFull":"Jacquard is a small programming language designed for a regime in which most code is written by machine-learning models and reviewed by people.","homepage":"","avatar":"https://avatars.githubusercontent.com/u/1551322?v=4","ghUrl":"https://github.com/jbwinters/jacquard-lang","defaultBranch":"main","watchers":0,"langs":[{"name":"OCaml","color":"#ef7a08","pct":86},{"name":"C","color":"#555555","pct":5},{"name":"Raku","color":"#0000fb","pct":5},{"name":"Perl","color":"#0298c3","pct":2},{"name":"Python","color":"#3572A5","pct":1},{"name":"Shell","color":"#89e051","pct":1}],"hnPosts":[{"title":"Show HN: Jacquard, a programming language for AI-written, human-reviewed code","points":102,"comments":58,"url":"https://github.com/jbwinters/jacquard-lang","objectID":"48894630","date":"2026-07-13"}],"awesomeIn":[],"starsSeries":[["2026-07-14",93],["2026-07-20",93]]}