{"id":"jonbarron__jonbarron.github.io","name":"jonbarron.github.io","owner":"jonbarron","desc":"","lang":"HTML","langColor":"#e34c26","stars":3603,"forks":2994,"issues":14,"d7":1,"boot":false,"vel":1,"score":6.066,"cats":[],"lists":0,"hn":null,"license":null,"created":"2017-02-16","pushed":"2026-04-24","topics":[],"isNew":false,"descFull":"","homepage":"","avatar":"https://avatars.githubusercontent.com/u/889526?v=4","ghUrl":"https://github.com/jonbarron/jonbarron.github.io","defaultBranch":"master","langs":[{"name":"HTML","color":"#e34c26","pct":100}],"hnPosts":[],"awesomeIn":[],"starsSeries":[["2026-06-21",3597],["2026-06-27",3602],["2026-07-03",3603]]}