{"id":"lagadic__visp","name":"visp","owner":"lagadic","desc":"Open Source Visual Servoing Platform","lang":"C++","langColor":"#f34b7d","stars":896,"forks":310,"issues":4,"d7":1,"boot":false,"vel":1,"score":7.202,"cats":["ai"],"lists":0,"hn":null,"license":"GPL-2.0","created":"2015-09-15","pushed":"2026-07-18","topics":["c-plus-plus","computer-vision","visp","visual-servoing"],"isNew":false,"descFull":"Open Source Visual Servoing Platform","homepage":"https://visp.inria.fr/","avatar":"https://avatars.githubusercontent.com/u/1417002?v=4","ghUrl":"https://github.com/lagadic/visp","defaultBranch":"master","langs":[{"name":"C++","color":"#f34b7d","pct":100}],"hnPosts":[],"awesomeIn":[],"starsSeries":[["2026-06-21",893],["2026-06-27",893],["2026-07-03",894],["2026-07-10",895],["2026-07-16",896]]}