{"id":"mongodb__node-mongodb-native","name":"node-mongodb-native","owner":"mongodb","desc":"The official MongoDB Node.js driver","lang":"TypeScript","langColor":"#3178c6","stars":10178,"forks":1818,"issues":34,"d7":1,"boot":false,"vel":1,"score":8.551,"cats":["database"],"lists":0,"hn":null,"license":"Apache-2.0","created":"2010-01-07","pushed":"2026-06-25","topics":["database","mongodb","node-js","nodejs","nosql"],"isNew":false,"descFull":"The official MongoDB Node.js driver","homepage":"https://www.mongodb.com/docs/drivers/node/current/","avatar":"https://avatars.githubusercontent.com/u/45120?v=4","ghUrl":"https://github.com/mongodb/node-mongodb-native","defaultBranch":"main","watchers":250,"langs":[{"name":"TypeScript","color":"#3178c6","pct":92},{"name":"JavaScript","color":"#f1e05a","pct":6},{"name":"Shell","color":"#89e051","pct":1},{"name":"Python","color":"#3572A5","pct":0},{"name":"Makefile","color":"#427819","pct":0}],"hnPosts":[],"awesomeIn":[],"starsSeries":[["2026-06-20",10177],["2026-06-26",10178]]}