{"id":"moodle__moodle","name":"moodle","owner":"moodle","desc":"Moodle - the world's open source learning platform","lang":"PHP","langColor":"#4F5D95","stars":7283,"forks":7562,"issues":1,"d7":14,"boot":false,"vel":14,"score":11.069,"cats":[],"lists":0,"hn":null,"license":"GPL-3.0","created":"2009-12-16","pushed":"2026-07-22","topics":[],"isNew":false,"descFull":"Moodle - the world's open source learning platform","homepage":"https://moodle.org/","avatar":"https://avatars.githubusercontent.com/u/168672?v=4","ghUrl":"https://github.com/moodle/moodle","defaultBranch":"main","watchers":432,"langs":[{"name":"PHP","color":"#4F5D95","pct":86},{"name":"JavaScript","color":"#f1e05a","pct":9},{"name":"Gherkin","color":"#5B2063","pct":2},{"name":"CSS","color":"#663399","pct":1},{"name":"Mustache","color":"#724b3b","pct":1},{"name":"SCSS","color":"#c6538c","pct":0}],"hnPosts":[],"awesomeIn":[],"starsSeries":[["2026-06-21",7197],["2026-06-27",7213],["2026-07-03",7230],["2026-07-10",7245],["2026-07-16",7267],["2026-07-22",7283]]}