{"id":"MTTECHTH__mihon-aria","name":"mihon-aria","owner":"MTTECHTH","desc":"The Ultimate Manga Reading Experience for Android 2026","lang":"HTML","langColor":"#e34c26","stars":151,"forks":0,"issues":0,"d7":0,"boot":false,"vel":0,"score":5.233,"cats":["mobile"],"lists":0,"hn":null,"license":null,"created":"2026-06-28","pushed":"2026-07-11","topics":["android","kotlin","manga","manga-downloader","manga-reader","mangadownloader"],"isNew":true,"descFull":"The Ultimate Manga Reading Experience for Android 2026","homepage":"","avatar":"https://avatars.githubusercontent.com/u/288195273?v=4","ghUrl":"https://github.com/MTTECHTH/mihon-aria","defaultBranch":"main","langs":[{"name":"HTML","color":"#e34c26","pct":100}],"hnPosts":[],"awesomeIn":[],"starsSeries":[["2026-07-01",151],["2026-07-07",151]]}