{"id":"OpenBMB__MiniCPM-V-Apps","name":"MiniCPM-V-Apps","owner":"OpenBMB","desc":"MiniCPM-V apps — fully offline multimodal chat on iOS / Android / HarmonyOS","lang":"Swift","langColor":"#F05138","stars":327,"forks":48,"issues":14,"d7":1,"boot":false,"vel":1,"score":7.063,"cats":["mobile"],"lists":0,"hn":null,"license":null,"created":"2025-08-05","pushed":"2026-07-01","topics":["android","harmonyos","ios","minicpm","minicpm-v"],"isNew":true,"descFull":"MiniCPM-V apps — fully offline multimodal chat on iOS / Android / HarmonyOS","homepage":"","avatar":"https://avatars.githubusercontent.com/u/89920203?v=4","ghUrl":"https://github.com/OpenBMB/MiniCPM-V-Apps","defaultBranch":"main","langs":[{"name":"Swift","color":"#F05138","pct":100}],"hnPosts":[],"awesomeIn":[],"starsSeries":[["2026-06-21",322],["2026-06-27",326],["2026-07-03",327]]}