{"id":"OSGeo__grass","name":"grass","owner":"OSGeo","desc":"GRASS - free and open-source geospatial processing engine","lang":"C","langColor":"#555555","stars":1143,"forks":433,"issues":711,"d7":1,"boot":false,"vel":1,"score":7.31,"cats":["science"],"lists":0,"hn":null,"license":null,"created":"2019-05-17","pushed":"2026-07-02","topics":["arrays","data-science","earth-observation","geospatial","geospatial-analysis","gis"],"isNew":false,"descFull":"GRASS - free and open-source geospatial processing engine","homepage":"https://grass.osgeo.org","avatar":"https://avatars.githubusercontent.com/u/1058467?v=4","ghUrl":"https://github.com/OSGeo/grass","defaultBranch":"main","langs":[{"name":"C","color":"#555555","pct":100}],"hnPosts":[],"awesomeIn":[],"starsSeries":[["2026-06-21",1140],["2026-06-27",1142],["2026-07-03",1143]]}