{"id":"outfox__2dog","name":"2dog","owner":"outfox","desc":"🦴 2dog is Godot in .NET","lang":"C#","langColor":"#178600","stars":121,"forks":10,"issues":3,"d7":5,"boot":true,"vel":5,"score":9.075,"cats":["games"],"lists":0,"hn":null,"license":"MIT","created":"2026-01-10","pushed":"2026-07-13","topics":["csharp","dotnet","gamedev","godot","godot-engine","godot4"],"isNew":true,"descFull":"🦴 2dog is Godot in .NET","homepage":"https://2dog.dev/","avatar":"https://avatars.githubusercontent.com/u/171872197?v=4","ghUrl":"https://github.com/outfox/2dog","defaultBranch":"main","watchers":2,"langs":[{"name":"C#","color":"#178600","pct":100}],"hnPosts":[],"awesomeIn":[],"starsSeries":[["2026-07-14",121]]}