{"id":"pubkey__rxdb","name":"rxdb","owner":"pubkey","desc":"The local-first database that runs on every JS runtime and replicates with your existing backend - no vendor, no lock-in - https://rxdb.info/","lang":"TypeScript","langColor":"#3178c6","stars":23242,"forks":1164,"issues":16,"d7":1,"boot":false,"vel":1,"score":9.372,"cats":["mobile","database","web"],"lists":1,"hn":null,"license":"Apache-2.0","created":"2016-12-02","pushed":"2026-06-28","topics":["angular","browser-database","couchdb","crdt","database","firebase"],"isNew":false,"descFull":"The local-first database that runs on every JS runtime and replicates with your existing backend - no vendor, no lock-in - https://rxdb.info/","homepage":"https://rxdb.info/","avatar":"https://avatars.githubusercontent.com/u/8926560?v=4","ghUrl":"https://github.com/pubkey/rxdb","defaultBranch":"master","watchers":204,"langs":[{"name":"TypeScript","color":"#3178c6","pct":93},{"name":"CSS","color":"#663399","pct":4},{"name":"JavaScript","color":"#f1e05a","pct":3},{"name":"Dart","color":"#00B4AB","pct":0},{"name":"Shell","color":"#89e051","pct":0},{"name":"HTML","color":"#e34c26","pct":0}],"hnPosts":[],"awesomeIn":[{"list":"react","label":"Awesome React","emoji":"⚛️","heading":"React State Management and Data Fetching","category":"web"}],"starsSeries":[["2026-06-20",23241],["2026-06-26",23242]]}