{"id":"pyjanitor-devs__pyjanitor","name":"pyjanitor","owner":"pyjanitor-devs","desc":"Clean APIs for data cleaning. Python implementation of R package Janitor","lang":"Python","langColor":"#3572A5","stars":1497,"forks":186,"issues":110,"d7":3,"boot":true,"vel":3,"score":8.408,"cats":["science"],"lists":0,"hn":null,"license":"MIT","created":"2018-03-04","pushed":"2026-06-23","topics":["cleaning-data","data","data-engineering","dataframe","hacktoberfest","pandas"],"isNew":false,"descFull":"Clean APIs for data cleaning. Python implementation of R package Janitor","homepage":"https://pyjanitor-devs.github.io/pyjanitor","avatar":"https://avatars.githubusercontent.com/u/53411673?v=4","ghUrl":"https://github.com/pyjanitor-devs/pyjanitor","defaultBranch":"dev","watchers":15,"langs":[{"name":"Python","color":"#3572A5","pct":97},{"name":"Jupyter Notebook","color":"#DA5B0B","pct":3},{"name":"Dockerfile","color":"#384d54","pct":0},{"name":"Makefile","color":"#427819","pct":0},{"name":"CSS","color":"#663399","pct":0}],"hnPosts":[],"awesomeIn":[],"starsSeries":[["2026-06-21",1497]]}