{"id":"react-navigation__react-navigation","name":"react-navigation","owner":"react-navigation","desc":"Routing and navigation for React Native and Web apps","lang":"TypeScript","langColor":"#3178c6","stars":24491,"forks":5125,"issues":837,"d7":1,"boot":false,"vel":1,"score":9.43,"cats":["mobile","web"],"lists":1,"hn":null,"license":null,"created":"2017-01-26","pushed":"2026-07-20","topics":["navigation","react","react-native","react-navigation"],"isNew":false,"descFull":"Routing and navigation for React Native and Web apps","homepage":"https://reactnavigation.org","avatar":"https://avatars.githubusercontent.com/u/29647600?v=4","ghUrl":"https://github.com/react-navigation/react-navigation","defaultBranch":"main","watchers":302,"langs":[{"name":"TypeScript","color":"#3178c6","pct":98},{"name":"Swift","color":"#F05138","pct":1},{"name":"JavaScript","color":"#f1e05a","pct":0},{"name":"Objective-C++","color":"#6866fb","pct":0},{"name":"Kotlin","color":"#A97BFF","pct":0},{"name":"C++","color":"#f34b7d","pct":0}],"hnPosts":[],"awesomeIn":[{"list":"react","label":"Awesome React","emoji":"⚛️","heading":"React Native Navigation","category":"web"}],"starsSeries":[["2026-06-21",24486],["2026-06-27",24489],["2026-07-03",24491],["2026-07-10",24489],["2026-07-16",24491]]}