{"id":"rust-unofficial__awesome-rust","name":"awesome-rust","owner":"rust-unofficial","desc":"A curated list of Rust code and resources.","lang":"Rust","langColor":"#dea584","stars":58242,"forks":3475,"issues":11,"d7":43,"boot":false,"vel":43,"score":13.833,"cats":[],"lists":0,"hn":null,"license":"CC0-1.0","created":"2014-07-17","pushed":"2026-07-09","topics":["awesome","rust"],"isNew":false,"descFull":"A curated list of Rust code and resources.","homepage":"","avatar":"https://avatars.githubusercontent.com/u/20820960?v=4","ghUrl":"https://github.com/rust-unofficial/awesome-rust","defaultBranch":"main","watchers":813,"langs":[{"name":"Rust","color":"#dea584","pct":100}],"hnPosts":[],"awesomeIn":[],"starsSeries":[["2026-06-20",58014],["2026-06-26",58097],["2026-07-02",58193],["2026-07-08",58242]]}