{"id":"spacejam__sled","name":"sled","owner":"spacejam","desc":"the champagne of beta embedded databases","lang":"Rust","langColor":"#dea584","stars":9038,"forks":426,"issues":171,"d7":4,"boot":false,"vel":4,"score":7.761,"cats":["database"],"lists":0,"hn":null,"license":"Apache-2.0","created":"2016-01-11","pushed":"2026-04-04","topics":["b-plus-tree","b-tree","concurrent","crash-testing","database","embedded-kv"],"isNew":false,"descFull":"the champagne of beta embedded databases","homepage":"","avatar":"https://avatars.githubusercontent.com/u/1505488?v=4","ghUrl":"https://github.com/spacejam/sled","defaultBranch":"main","watchers":125,"langs":[{"name":"Rust","color":"#dea584","pct":98},{"name":"Python","color":"#3572A5","pct":1},{"name":"Shell","color":"#89e051","pct":1}],"hnPosts":[],"awesomeIn":[],"starsSeries":[["2026-06-20",9035],["2026-06-26",9038]]}