{"id":"spring-projects__spring-security","name":"spring-security","owner":"spring-projects","desc":"Spring Security","lang":"Java","langColor":"#b07219","stars":9534,"forks":6287,"issues":1399,"d7":13,"boot":true,"vel":13,"score":11.175,"cats":["security"],"lists":0,"hn":null,"license":"Apache-2.0","created":"2012-01-10","pushed":"2026-06-19","topics":["framework","java","security","spring","spring-framework"],"isNew":false,"descFull":"Spring Security","homepage":"http://spring.io/projects/spring-security","avatar":"https://avatars.githubusercontent.com/u/317776?v=4","ghUrl":"https://github.com/spring-projects/spring-security","defaultBranch":"main","langs":[{"name":"Java","color":"#b07219","pct":100}],"hnPosts":[],"awesomeIn":[],"starsSeries":[["2026-06-20",9534]]}