{"id":"vaadin__hilla","name":"hilla","owner":"vaadin","desc":"Build better business applications, faster. No more juggling REST endpoints or deciphering GraphQL queries. Hilla seamlessly connects Spring Boot and React to …","lang":"Java","langColor":"#b07219","stars":984,"forks":78,"issues":438,"d7":0,"boot":false,"vel":0,"score":6.278,"cats":["web"],"lists":0,"hn":null,"license":"Apache-2.0","created":"2021-04-27","pushed":"2026-07-06","topics":["client-side","frontend","java","lit","lit-element","react"],"isNew":false,"descFull":"Build better business applications, faster. No more juggling REST endpoints or deciphering GraphQL queries. Hilla seamlessly connects Spring Boot and React to accelerate application development.","homepage":"https://hilla.dev","avatar":"https://avatars.githubusercontent.com/u/1171922?v=4","ghUrl":"https://github.com/vaadin/hilla","defaultBranch":"main","langs":[{"name":"Java","color":"#b07219","pct":100}],"hnPosts":[],"awesomeIn":[],"starsSeries":[["2026-06-21",983],["2026-06-27",984],["2026-07-03",984]]}