{"id":"vesoft-inc__nebula","name":"nebula","owner":"vesoft-inc","desc":"A distributed, fast open-source graph database featuring horizontal scalability and high availability","lang":"C++","langColor":"#f34b7d","stars":12291,"forks":1323,"issues":678,"d7":11,"boot":false,"vel":11,"score":9.404,"cats":["database"],"lists":0,"hn":null,"license":"Apache-2.0","created":"2018-08-28","pushed":"2026-05-18","topics":["big-data","cpp","database","distributed","distributed-systems","graph"],"isNew":false,"descFull":"  A distributed, fast open-source graph database featuring horizontal scalability and high availability","homepage":"https://nebula-graph.io","avatar":"https://avatars.githubusercontent.com/u/42441426?v=4","ghUrl":"https://github.com/vesoft-inc/nebula","defaultBranch":"master","watchers":186,"langs":[{"name":"C++","color":"#f34b7d","pct":66},{"name":"Gherkin","color":"#5B2063","pct":28},{"name":"Python","color":"#3572A5","pct":3},{"name":"CMake","color":"#DA3434","pct":1},{"name":"Yacc","color":"#4B6C4B","pct":1},{"name":"Thrift","color":"#D12127","pct":0}],"hnPosts":[],"awesomeIn":[],"starsSeries":[["2026-06-20",12245],["2026-06-26",12253],["2026-07-02",12263],["2026-07-08",12277],["2026-07-14",12291]]}