{"id":"winapps-org__winapps","name":"winapps","owner":"winapps-org","desc":"Run Windows apps such as Microsoft Office/Adobe in Linux (Ubuntu/Fedora) and GNOME/KDE as if they were a part of the native OS, including Nautilus integration.…","lang":"Shell","langColor":"#89e051","stars":15517,"forks":494,"issues":76,"d7":50,"boot":false,"vel":50,"score":13.025,"cats":["cloud"],"lists":0,"hn":null,"license":null,"created":"2023-07-05","pushed":"2026-07-07","topics":["cassowary","docker","freerdp","gnome","hacktoberfest","integration"],"isNew":false,"descFull":" Run Windows apps such as Microsoft Office/Adobe in Linux (Ubuntu/Fedora) and GNOME/KDE as if they were a part of the native OS, including Nautilus integration. Hard fork of https://github.com/Fmstrat/winapps/","homepage":"","avatar":"https://avatars.githubusercontent.com/u/138696776?v=4","ghUrl":"https://github.com/winapps-org/winapps","defaultBranch":"main","watchers":66,"langs":[{"name":"Shell","color":"#89e051","pct":86},{"name":"PowerShell","color":"#012456","pct":9},{"name":"Nix","color":"#7e7eff","pct":3},{"name":"Batchfile","color":"#C1F12E","pct":2}],"hnPosts":[],"awesomeIn":[],"starsSeries":[["2026-06-20",15399],["2026-06-26",15421],["2026-07-02",15439],["2026-07-08",15517]]}