{"id":"xm1k3__cent","name":"cent","owner":"xm1k3","desc":"Community edition nuclei templates, a simple tool that allows you to organize all the Nuclei templates offered by the community in one place","lang":"Go","langColor":"#00ADD8","stars":1044,"forks":166,"issues":0,"d7":-1,"boot":false,"vel":0,"score":5.341,"cats":["security"],"lists":0,"hn":null,"license":"Apache-2.0","created":"2021-05-31","pushed":"2026-06-06","topics":["bugbounty","golang","hacktoberfest","nuclei","nuclei-templates","penetration-testing"],"isNew":false,"descFull":"Community edition nuclei templates, a simple tool that allows you to organize all the Nuclei templates offered by the community in one place","homepage":"","avatar":"https://avatars.githubusercontent.com/u/73166077?v=4","ghUrl":"https://github.com/xm1k3/cent","defaultBranch":"main","watchers":23,"langs":[{"name":"Go","color":"#00ADD8","pct":100}],"hnPosts":[],"awesomeIn":[],"starsSeries":[["2026-06-21",1045],["2026-06-27",1044]]}